pyTrendyol/Kategori.py
pyTrendyol/Modeller.py
pyTrendyol/Urun.py
pyTrendyol/__init__.py
pyTrendyol-0.0.5.dist-info/LICENSE
pyTrendyol-0.0.5.dist-info/METADATA
pyTrendyol-0.0.5.dist-info/WHEEL
pyTrendyol-0.0.5.dist-info/top_level.txt
pyTrendyol-0.0.5.dist-info/RECORD
