Metadata-Version: 2.1
Name: pyTrendyol
Version: 0.0.5
Summary: Trendyol'dan veri almayı kolaylaştırmak için tasarlanan kütüphane.
Home-page: https://github.com/keyiflerolsun/pyTrendyol
Author: keyiflerolsun
Author-email: keyiflerolsun@gmail.com
License: GPLv3+
Keywords: pyTrendyol,KekikAkademi,keyiflerolsun
Classifier: Development Status :: 5 - Production/Stable
Classifier: License :: OSI Approved :: GNU General Public License v3 or later (GPLv3+)
Classifier: Programming Language :: Python :: 3
Requires-Python: >=3.10
License-File: LICENSE
Requires-Dist: pip
Requires-Dist: setuptools
Requires-Dist: wheel
Requires-Dist: Kekik
Requires-Dist: requests
Requires-Dist: parsel
Requires-Dist: pydantic
